CHANGELOG.rst
LICENSE.txt
MANIFEST.in
README.rst
TODO.txt
VERSION.txt
setup.cfg
setup.py
doc/manual.rst
pyramid_pagination/__init__.py
pyramid_pagination/decoder.py
pyramid_pagination/engine.py
pyramid_pagination/mapper.py
pyramid_pagination/paginator.py
pyramid_pagination/test.py
pyramid_pagination.egg-info/PKG-INFO
pyramid_pagination.egg-info/SOURCES.txt
pyramid_pagination.egg-info/dependency_links.txt
pyramid_pagination.egg-info/requires.txt
pyramid_pagination.egg-info/top_level.txt
pyramid_pagination.egg-info/zip-safe