Metadata-Version: 1.1
Name: pyramid-pagination
Version: 0.1.1
Summary: Easy pagination for Pyramid applications
Home-page: http://github.com/canaryhealth/pyramid_pagination
Author: Philip J Grabner, Canary Health Inc
Author-email: pjg.github@ubergrabner.net
License: MIT (http://opensource.org/licenses/MIT)
Keywords: pyramid application pagination paging
Platform: any
Classifier: Development Status :: 1 - Planning
Classifier: Intended Audience :: Developers
Classifier: Programming Language :: Python
Classifier: Operating System :: OS Independent
Classifier: Natural Language :: English
Classifier: License :: OSI Approved :: MIT License
Classifier: License :: Public Domain
